[
    {
        "title": "Mulyadi и Purnawan приняли формы Cabup-Cawabup в DPC Pdip Tabanan",
        "link": "https://www.kilasbali.com/2024/04/25/mulyadi-dan-purnawan-ambil-formulir-cabup-cawabup-di-dpc-pdip-tabanan/",
        "date": "25 April 2024 12:00"
    },
    {
        "title": "Sinergi Bkkbn Bali и BKL держит ориентацию PJP для пожилых людей",
        "link": "https://www.kilasbali.com/2024/04/25/sinergi-bkkbn-bali-dan-bkl-gelar-orientasi-pjp-bagi-lansia/",
        "date": "25 April 2024 12:00"
    },
    {
        "title": "Иностранцы завершают мотоцикл в комплекте с инструкторами",
        "link": "https://www.kilasbali.com/2024/04/25/wna-sewakan-motor-lengkap-dengan-instruktur/",
        "date": "25 April 2024 12:00"
    },
    {
        "title": "Предположительно, ударил молнией, Пура Рату Геде Бима Сакти в огне",
        "link": "https://www.kilasbali.com/2024/04/25/diduga-tersambar-petir-pura-ratu-gede-bima-sakti-di-beraban-kebakaran/",
        "date": "25 April 2024 12:00"
    },
    {
        "title": "Edi Wirawan взимает форму Bacawabup в DPC Pdip Tabanan",
        "link": "https://www.kilasbali.com/2024/04/25/65185/",
        "date": "25 April 2024 12:00"
    },
    {
        "title": "Pdip-Golkar Tabanan Покажите сигнал коалиции в Pilkada 2024",
        "link": "https://www.kilasbali.com/2024/04/24/pdip-golkar-tabanan-tunjukkan-sinyal-koalisi-di-pilkada-2024/",
        "date": "24 April 2024 12:00"
    },
    {
        "title": "Тукад Йе Матан переполнен, два жителя были почти тащили течением",
        "link": "https://www.kilasbali.com/2024/04/24/tukad-yeh-matan-meluap-dua-warga-nyaris-terseret-arus/",
        "date": "24 April 2024 12:00"
    },
    {
        "title": "Коробка безопасности гондола Resto, этот человек был арестован полицией",
        "link": "https://www.kilasbali.com/2024/04/24/gondol-safety-box-resto-pria-ini-ditangkap-polisi/",
        "date": "24 April 2024 12:00"
    },
    {
        "title": "Nyuwun Banten Pajegan 2,7 AD, эта женщина охранялась",
        "link": "https://www.kilasbali.com/2024/04/24/nyuwun-banten-pajegan-27-m-perempuan-ini-dikawal-ketat/",
        "date": "24 April 2024 12:00"
    },
    {
        "title": "«Полиция ходит в школу» предотвратить и обнаружить «издевательства» в SD",
        "link": "https://www.kilasbali.com/2024/04/23/police-go-to-school-cegah-dan-deteksi-bullying-di-sd/",
        "date": "23 April 2024 12:00"
    },
    {
        "title": "2024 Pilkada, KPU предлагает позицию PPK",
        "link": "https://www.kilasbali.com/2024/04/23/pilkada-2024-kpu-tawarkan-posisi-ppk/",
        "date": "23 April 2024 12:00"
    }
]